dropbucket/__init__.py
dropbucket/cli.py
dropbucket/dropbucket.py
dropbucket/models/__init__.py
dropbucket/models/dropbucket_clustering.py
dropbucket/models/dropbucket_doublet.py
dropbucket-0.1.7.dist-info/licenses/LICENSE
dropbucket-0.1.7.dist-info/METADATA
dropbucket-0.1.7.dist-info/WHEEL
dropbucket-0.1.7.dist-info/entry_points.txt
dropbucket-0.1.7.dist-info/top_level.txt
dropbucket-0.1.7.dist-info/RECORD
