Metadata-Version: 2.4
Name: dropbucket
Version: 0.1.7
Summary: Robust SNP-based demultiplexing tool
Author-email: dongjuleem <ehdwn5170@g.skku.edu>
Maintainer-email: dongjuleem <ehdwn5170@g.skku.edu>
License: MIT
Requires-Python: >=3.9
License-File: LICENSE
Requires-Dist: numpy==1.26.4
Requires-Dist: pandas==2.2.3
Requires-Dist: scipy==1.13.1
Requires-Dist: scikit-learn==1.6.1
Dynamic: license-file
